keycloak_oidc_api_client/__init__.py
keycloak_oidc_api_client/api/__init__.py
keycloak_oidc_api_client/api/default/__init__.py
keycloak_oidc_api_client/api/default/generate_user_code.py
keycloak_oidc_api_client/api/default/get_well_known.py
keycloak_oidc_api_client/api/default/request_token.py
keycloak_oidc_api_client/client.py
keycloak_oidc_api_client/errors.py
keycloak_oidc_api_client/models/__init__.py
keycloak_oidc_api_client/models/error.py
keycloak_oidc_api_client/models/mtls_endpoint_aliases.py
keycloak_oidc_api_client/models/request_token.py
keycloak_oidc_api_client/models/request_token_response.py
keycloak_oidc_api_client/models/user_code_request.py
keycloak_oidc_api_client/models/user_code_response.py
keycloak_oidc_api_client/models/well_known.py
keycloak_oidc_api_client/py.typed
keycloak_oidc_api_client/types.py
keycloak_oidc_api_client-1.1.0.dist-info/METADATA
keycloak_oidc_api_client-1.1.0.dist-info/WHEEL
keycloak_oidc_api_client-1.1.0.dist-info/licenses/LICENSE
keycloak_oidc_api_client-1.1.0.dist-info/licenses/NOTICE
keycloak_oidc_api_client-1.1.0.dist-info/RECORD
